ravi_utils/__init__.py
ravi_utils/common.py
ravi_utils/common_conf.py
ravi_utils/common_files.py
ravi_utils/common_logging.py
ravi_utils/common_net.py
ravi_utils-0.1.6.dist-info/LICENSE
ravi_utils-0.1.6.dist-info/METADATA
ravi_utils-0.1.6.dist-info/WHEEL
ravi_utils-0.1.6.dist-info/top_level.txt
ravi_utils-0.1.6.dist-info/RECORD
