Metadata-Version: 2.1
Name: ravi-utils
Version: 0.1.6
Summary: Common functions package for simple scripts
Home-page: https://github.com/raulviigipuu/ravi_utils
Author: Raul Viigipuu
Author-email: raul@viigipuu.ee
License: UNKNOWN
Platform: UNKNOWN
Classifier: Programming Language :: Python :: 3
Classifier: License :: OSI Approved :: MIT License
Classifier: Operating System :: OS Independent
